pydantic_argparse/__init__.py
pydantic_argparse/__metadata__.py
pydantic_argparse/py.typed
pydantic_argparse/argparse/__init__.py
pydantic_argparse/argparse/actions.py
pydantic_argparse/argparse/parser.py
pydantic_argparse/compatibility/__init__.py
pydantic_argparse/compatibility/argparse.py
pydantic_argparse/compatibility/pydantic.py
pydantic_argparse/parsers/__init__.py
pydantic_argparse/parsers/boolean.py
pydantic_argparse/parsers/command.py
pydantic_argparse/parsers/container.py
pydantic_argparse/parsers/enum.py
pydantic_argparse/parsers/literal.py
pydantic_argparse/parsers/mapping.py
pydantic_argparse/parsers/standard.py
pydantic_argparse/utils/__init__.py
pydantic_argparse/utils/arguments.py
pydantic_argparse/utils/errors.py
pydantic_argparse/utils/namespaces.py
pydantic_argparse/utils/pydantic.py
pydantic_argparse/utils/types.py
pydantic_argparse-0.9.0.dist-info/METADATA
pydantic_argparse-0.9.0.dist-info/WHEEL
pydantic_argparse-0.9.0.dist-info/licenses/LICENSE
pydantic_argparse-0.9.0.dist-info/RECORD
