Metadata-Version: 2.3
Name: pydantic-argparse
Version: 0.9.0
Summary: Typed Argument Parsing with Pydantic
Project-URL: Homepage, https://pydantic-argparse.supimdos.com
Project-URL: Documentation, https://pydantic-argparse.supimdos.com
Project-URL: Changelog, https://github.com/SupImDos/pydantic-argparse/blob/master/CHANGELOG.md
Project-URL: Repository, https://github.com/SupImDos/pydantic-argparse
Project-URL: Issues, https://github.com/SupImDos/pydantic-argparse/issues
Author-email: Hayden Richards <supimdos@gmail.com>
License: MIT License
License-File: LICENSE
Keywords: argparse,pydantic,python,typed,validation
Classifier: Development Status :: 4 - Beta
Classifier: Framework :: Pydantic
Classifier: Intended Audience :: Developers
Classifier: License :: OSI Approved :: MIT License
Classifier: Programming Language :: Python
Classifier: Programming Language :: Python :: 3
Classifier: Programming Language :: Python :: 3.8
Classifier: Programming Language :: Python :: 3.9
Classifier: Programming Language :: Python :: 3.10
Classifier: Programming Language :: Python :: 3.11
Classifier: Programming Language :: Python :: 3.12
Classifier: Topic :: Software Development :: Libraries :: Python Modules
Requires-Python: >=3.8
Requires-Dist: pydantic
